techspec_extract/__init__.py
techspec_extract/main.py
techspec_extract/prompts.py
techspec_extract-2025.12.21115447.dist-info/METADATA
techspec_extract-2025.12.21115447.dist-info/WHEEL
techspec_extract-2025.12.21115447.dist-info/top_level.txt
techspec_extract-2025.12.21115447.dist-info/RECORD
