Metadata-Version: 2.4
Name: techspec-extract
Version: 2025.12.21115447
Summary: A new package designed to process user input descriptions of technical products or components and generate structured summaries or specifications. It leverages LLMs to interpret the input text and ext
Author-email: techspec-extract <hi@eugene.plus>
License: MIT
Project-URL: Homepage, https://github.com/chigwell/techspec-extract
Requires-Python: >=3.9
Requires-Dist: langchain-llm7>=0.0.0
Requires-Dist: llmatch-messages>=0.0.0
Requires-Dist: langchain-core>=0.3.0
